rites/__init__.py
rites/_version.py
rites/chrono.py
rites/logger.py
rites/rituals.py
rites/test.py
rites/bitchain/__init__.py
rites/bitchain/bitchain.py
rites/chrono/__init__.py
rites/chrono/chrono.py
rites/logger/__init__.py
rites/logger/logger.py
rites/rituals/__init__.py
rites/rituals/math.py
rites/rituals/printer.py
rites/rituals/spells.py
rites-0.5.3.dist-info/LICENSE
rites-0.5.3.dist-info/METADATA
rites-0.5.3.dist-info/WHEEL
rites-0.5.3.dist-info/top_level.txt
rites-0.5.3.dist-info/RECORD
