Metadata-Version: 2.1
Name: rites
Version: 0.5.3
Summary: Reclipse's Initial Try at Enhanced Simplicity or R.I.T.E.S. A simple and lightweight QoL module.
Home-page: https://github.com/ReclipseTheOne/rites
Author: Reclipse
Maintainer: Reclipse
Classifier: Programming Language :: Python :: 3
Classifier: License :: OSI Approved :: GNU Affero General Public License v3 or later (AGPLv3+)
Classifier: Operating System :: OS Independent
Requires-Python: >=3.6
License-File: LICENSE
Requires-Dist: colored>=2.2.4
